MANIFEST.in
README.txt
development.ini
setup.cfg
setup.py
Paste-1.7.3.1-py2.6.egg/paste/evalexception/media/MochiKit.packed.js
Paste-1.7.3.1-py2.6.egg/paste/evalexception/media/debug.js
Paste-1.7.3.1-py2.6.egg/paste/evalexception/media/minus.jpg
Paste-1.7.3.1-py2.6.egg/paste/evalexception/media/plus.jpg
acr/__init__.py
acr/websetup.py
acr.egg-info/PKG-INFO
acr.egg-info/SOURCES.txt
acr.egg-info/dependency_links.txt
acr.egg-info/entry_points.txt
acr.egg-info/not-zip-safe
acr.egg-info/paster_plugins.txt
acr.egg-info/requires.txt
acr.egg-info/top_level.txt
acr/acr_plugins/__init__.py
acr/acr_plugins/Chpassword/__init__.py
acr/acr_plugins/Chpassword/index.html
acr/acr_plugins/Chpassword/static/Gnome-Dialog-Password-64.png
acr/acr_plugins/Chpassword/static/unbound.png
acr/acr_plugins/stroller/__init__.py
acr/acr_plugins/theme/__init__.py
acr/acr_plugins/theme/edit_css.html
acr/acr_plugins/theme/manage_themes.html
acr/acr_plugins/theme/upload_theme.html
acr/acr_plugins/theme/static/copy_theme.png
acr/acr_plugins/theme/static/delete.png
acr/acr_plugins/theme/static/edit_css.png
acr/acr_plugins/theme/static/switch_theme.png
acr/acr_plugins/theme/static/upload_theme.png
acr/config/__init__.py
acr/config/app_cfg.py
acr/config/environment.py
acr/config/middleware.py
acr/controllers/__init__.py
acr/controllers/error.py
acr/controllers/root.py
acr/i18n/it/LC_MESSAGES/acr.mo
acr/i18n/it/LC_MESSAGES/acr.po
acr/i18n/ru/LC_MESSAGES/acr.po
acr/lib/__init__.py
acr/lib/app_globals.py
acr/lib/base.py
acr/lib/helpers.py
acr/lib/multisite.py
acr/model/__init__.py
acr/model/auth.py
acr/public/favicon.ico
acr/public/css/style.css
acr/public/images/error.png
acr/public/images/info.png
acr/public/images/ok.png
acr/public/images/spinner.gif
acr/public/images/star.png
acr/public/images/warning.png
acr/templates/__init__.py
acr/templates/debug.html
acr/templates/error.html
acr/templates/login.html
acr/templates/master.html
public1/assets/1.jpg
public1/assets/1.mp4.png
public1/assets/1_big.png
public1/assets/1_huge.png
public1/assets/1_icon.png
public1/assets/1_medium.png
public1/assets/1_small.png
public1/rdisk/empty.txt
public1/themes/dragonfly/main.css
public1/themes/dragonfly/images/img01.gif
