Metadata-Version: 1.0
Name: acr
Version: 0.3.6
Summary: ACRCms is an open source Python web content management system based on Turbogears and libacr
Home-page: http://www.acrcms.org
Author: AXANT
Author-email: tech@axant.it
License: GPL
Keywords: turbogears2.application cms cmf web
Platform: UNKNOWN
Classifier: Development Status :: 4 - Beta
Classifier: Environment :: Web Environment
Classifier: Framework :: TurboGears
Classifier: License :: OSI Approved :: GNU General Public License (GPL)
Classifier: Operating System :: OS Independent
Classifier: Programming Language :: Python
Classifier: Topic :: Internet :: WWW/HTTP :: Dynamic Content
Classifier: Topic :: Software Development :: Libraries :: Python Modules
